gbn.py
gbn-0.4.3.dist-info/DESCRIPTION.rst
gbn-0.4.3.dist-info/METADATA
gbn-0.4.3.dist-info/RECORD
gbn-0.4.3.dist-info/WHEEL
gbn-0.4.3.dist-info/metadata.json
gbn-0.4.3.dist-info/top_level.txt
