Metadata-Version: 2.0
Name: gbn
Version: 0.4.3
Summary: Greenlet BottleNeck profiler.
Home-page: https://github.com/denis-ryzhkov/gbn
Author: Denis Ryzhkov
Author-email: denisr@denisr.com
License: MIT
Platform: UNKNOWN
Classifier: Development Status :: 4 - Beta
Classifier: License :: OSI Approved :: MIT License
Classifier: Operating System :: OS Independent
Classifier: Programming Language :: Python :: 2.7
Classifier: Topic :: Software Development :: Libraries :: Python Modules
Requires-Dist: greenlet
